{
  "title": "A Gentle Noble’s Vacation Recommendation (2026)",
  "url": "https://zoroto.com.in/anime/a-gentle-nobles-vacation-recommendation-2026/",
  "description": "When Lizel mysteriously finds himself in a city that bears odd similarities to his own but clearly isn’t, he quickly comes to terms with the unlikely truth: this is an entirely different world. Even so, laid-back Lizel isn’t the type to panic. He immediately sets out to learn more about this strange place, and to help him do so, hires a seasoned adventurer named Gil as his tour guide and protector.Until he’s able to find a way home, Lizel figures this is a perfect opportunity to explore a new wa",
  "genres": [],
  "status": null,
  "rating": null,
  "total_episodes": 4,
  "available_episodes": 4,
  "episodes": [
    {
      "episode_number": "1",
      "episode_url": "https://zoroto.com.in/a-gentle-nobles-vacation-recommendation-episode-1/",
      "episode_title": "1",
      "video_sources": [
        "https://gogoanime.com.by/streaming.php?id=a-gentle-nobles-vacation-recommendation-20281&ep=162253&server=hd-1&type=sub"
      ],
      "has_videos": true
    },
    {
      "episode_number": "2",
      "episode_url": "https://zoroto.com.in/a-gentle-nobles-vacation-recommendation-episode-2/",
      "episode_title": "2",
      "video_sources": [
        "https://gogoanime.com.by/streaming.php?id=a-gentle-nobles-vacation-recommendation-20281&ep=163297&server=hd-1&type=sub"
      ],
      "has_videos": true
    },
    {
      "episode_number": "3",
      "episode_url": "https://zoroto.com.in/a-gentle-nobles-vacation-recommendation-episode-3/",
      "episode_title": "3",
      "video_sources": [
        "https://gogoanime.com.by/streaming.php?id=a-gentle-nobles-vacation-recommendation-20281&ep=164149&server=hd-1&type=sub"
      ],
      "has_videos": true
    },
    {
      "episode_number": "4",
      "episode_url": "https://zoroto.com.in/a-gentle-nobles-vacation-recommendation-episode-4/",
      "episode_title": "4",
      "video_sources": [
        "https://gogoanime.com.by/streaming.php?id=a-gentle-nobles-vacation-recommendation-20281&ep=164913&server=hd-1&type=sub"
      ],
      "has_videos": true
    }
  ],
  "scraped_at": "2026-01-30 07:10:32"
}