{
  "title": "Bleach the Movie: The DiamondDust Rebellion",
  "url": "https://zoroto.com.in/anime/bleach-the-movie-the-diamonddust-rebellion/",
  "description": "Assigned to protect a royal procession transporting a powerful artifact called the “Ouin,” Squad 10 gathers in the human world as Captain Toushirou Hitsugaya and Lieutenant Rangiku Matsumoto observe the area cautiously. However, the caravan is suddenly struck by a group of assailants who wreak havoc on the procession, stealing the Ouin in the process. After a brief clash with one of the attackers, the distraught Hitsugaya pursues the escaping thieves, leaving behind Matsumoto and the disoriented",
  "genres": [],
  "status": null,
  "rating": null,
  "total_episodes": 1,
  "available_episodes": 1,
  "episodes": [
    {
      "episode_number": "1",
      "episode_url": "https://zoroto.com.in/bleach-the-movie-the-diamonddust-rebellion-episode-1/",
      "episode_title": "1",
      "video_sources": [
        "https://gogoanime.com.by/streaming.php?id=bleach-the-movie-the-diamonddust-rebellion-1669&ep=58324&server=hd-2&type=sub"
      ],
      "has_videos": true
    }
  ],
  "scraped_at": "2026-01-30 04:36:46"
}