{
  "title": "Kengan Ashura 2nd Season Part 2",
  "url": "https://zoroto.com.in/anime/kengan-ashura-2nd-season-part-2/",
  "description": "The second half of second season of Kengan Ashura.The end of the battle is near, and the Kengan Life-or-Death Tournament eagerly awaits its winner.",
  "genres": [],
  "status": null,
  "rating": null,
  "total_episodes": 16,
  "available_episodes": 16,
  "episodes": [
    {
      "episode_number": "1",
      "episode_url": "https://zoroto.com.in/kengan-ashura-2nd-season-part-2-episode-1/",
      "episode_title": "1",
      "video_sources": [
        "https://gogoanime.com.by/streaming.php?id=kengan-ashura-2nd-season-part-2-19201&ep=127444&server=hd-2&type=sub"
      ],
      "has_videos": true
    },
    {
      "episode_number": "2",
      "episode_url": "https://zoroto.com.in/kengan-ashura-2nd-season-part-2-episode-2/",
      "episode_title": "2",
      "video_sources": [
        "https://gogoanime.com.by/streaming.php?id=kengan-ashura-2nd-season-part-2-19201&ep=127445&server=hd-2&type=sub"
      ],
      "has_videos": true
    },
    {
      "episode_number": "3",
      "episode_url": "https://zoroto.com.in/kengan-ashura-2nd-season-part-2-episode-3/",
      "episode_title": "3",
      "video_sources": [
        "https://gogoanime.com.by/streaming.php?id=kengan-ashura-2nd-season-part-2-19201&ep=127446&server=hd-2&type=sub"
      ],
      "has_videos": true
    },
    {
      "episode_number": "4",
      "episode_url": "https://zoroto.com.in/kengan-ashura-2nd-season-part-2-episode-4/",
      "episode_title": "4",
      "video_sources": [
        "https://gogoanime.com.by/streaming.php?id=kengan-ashura-2nd-season-part-2-19201&ep=127447&server=hd-2&type=sub"
      ],
      "has_videos": true
    },
    {
      "episode_number": "5",
      "episode_url": "https://zoroto.com.in/kengan-ashura-2nd-season-part-2-episode-5/",
      "episode_title": "5",
      "video_sources": [
        "https://gogoanime.com.by/streaming.php?id=kengan-ashura-2nd-season-part-2-19201&ep=127448&server=hd-2&type=sub"
      ],
      "has_videos": true
    },
    {
      "episode_number": "6",
      "episode_url": "https://zoroto.com.in/kengan-ashura-2nd-season-part-2-episode-6/",
      "episode_title": "6",
      "video_sources": [
        "https://gogoanime.com.by/streaming.php?id=kengan-ashura-2nd-season-part-2-19201&ep=127449&server=hd-2&type=sub"
      ],
      "has_videos": true
    },
    {
      "episode_number": "7",
      "episode_url": "https://zoroto.com.in/kengan-ashura-2nd-season-part-2-episode-7/",
      "episode_title": "7",
      "video_sources": [
        "https://gogoanime.com.by/streaming.php?id=kengan-ashura-2nd-season-part-2-19201&ep=127450&server=hd-2&type=sub"
      ],
      "has_videos": true
    },
    {
      "episode_number": "8",
      "episode_url": "https://zoroto.com.in/kengan-ashura-2nd-season-part-2-episode-8/",
      "episode_title": "8",
      "video_sources": [
        "https://gogoanime.com.by/streaming.php?id=kengan-ashura-2nd-season-part-2-19201&ep=127451&server=hd-2&type=sub"
      ],
      "has_videos": true
    },
    {
      "episode_number": "9",
      "episode_url": "https://zoroto.com.in/kengan-ashura-2nd-season-part-2-episode-9/",
      "episode_title": "9",
      "video_sources": [
        "https://gogoanime.com.by/streaming.php?id=kengan-ashura-2nd-season-part-2-19201&ep=127452&server=hd-2&type=sub"
      ],
      "has_videos": true
    },
    {
      "episode_number": "10",
      "episode_url": "https://zoroto.com.in/kengan-ashura-2nd-season-part-2-episode-10/",
      "episode_title": "10",
      "video_sources": [
        "https://gogoanime.com.by/streaming.php?id=kengan-ashura-2nd-season-part-2-19201&ep=127453&server=hd-2&type=sub"
      ],
      "has_videos": true
    },
    {
      "episode_number": "11",
      "episode_url": "https://zoroto.com.in/kengan-ashura-2nd-season-part-2-episode-11/",
      "episode_title": "11",
      "video_sources": [
        "https://gogoanime.com.by/streaming.php?id=kengan-ashura-2nd-season-part-2-19201&ep=127454&server=hd-2&type=sub"
      ],
      "has_videos": true
    },
    {
      "episode_number": "12",
      "episode_url": "https://zoroto.com.in/kengan-ashura-2nd-season-part-2-episode-12/",
      "episode_title": "12",
      "video_sources": [
        "https://gogoanime.com.by/streaming.php?id=kengan-ashura-2nd-season-part-2-19201&ep=127455&server=hd-2&type=sub"
      ],
      "has_videos": true
    },
    {
      "episode_number": "13",
      "episode_url": "https://zoroto.com.in/kengan-ashura-2nd-season-part-2-episode-13/",
      "episode_title": "13",
      "video_sources": [
        "https://gogoanime.com.by/streaming.php?id=kengan-ashura-2nd-season-part-2-19201&ep=127456&server=hd-2&type=sub"
      ],
      "has_videos": true
    },
    {
      "episode_number": "14",
      "episode_url": "https://zoroto.com.in/kengan-ashura-2nd-season-part-2-episode-14/",
      "episode_title": "14",
      "video_sources": [
        "https://gogoanime.com.by/streaming.php?id=kengan-ashura-2nd-season-part-2-19201&ep=127457&server=hd-2&type=sub"
      ],
      "has_videos": true
    },
    {
      "episode_number": "15",
      "episode_url": "https://zoroto.com.in/kengan-ashura-2nd-season-part-2-episode-15/",
      "episode_title": "15",
      "video_sources": [
        "https://gogoanime.com.by/streaming.php?id=kengan-ashura-2nd-season-part-2-19201&ep=127458&server=hd-2&type=sub"
      ],
      "has_videos": true
    },
    {
      "episode_number": "16",
      "episode_url": "https://zoroto.com.in/kengan-ashura-2nd-season-part-2-episode-16/",
      "episode_title": "16",
      "video_sources": [
        "https://gogoanime.com.by/streaming.php?id=kengan-ashura-2nd-season-part-2-19201&ep=127459&server=hd-2&type=sub"
      ],
      "has_videos": true
    }
  ],
  "scraped_at": "2026-01-30 04:44:59"
}