{
  "title": "My Hero Academia 4 (2019)",
  "url": "https://zoroto.com.in/anime/my-hero-academia-4-2019/",
  "description": "After successfully passing his Provisional Hero License exam, Izuku “Deku” Midoriya seeks out an extracurricular internship with a professional hero agency. At the recommendation of his mentor All Might, Midoriya lands a position under All Might’s former sidekick, Sir Nighteye, now a famous hero in his own right.As Midoriya’s classmates further their own abilities through various internships, up-and-coming villain Kai Chisaki utilizes his terrifying powers to gather favor in the criminal underwo",
  "genres": [],
  "status": null,
  "rating": null,
  "total_episodes": 24,
  "available_episodes": 24,
  "episodes": [
    {
      "episode_number": "1",
      "episode_url": "https://zoroto.com.in/my-hero-academia-4-episode-1/",
      "episode_title": "1",
      "video_sources": [
        "https://gogoanime.com.by/streaming.php?id=my-hero-academia-4-365&ep=8497&server=hd-1&type=sub"
      ],
      "has_videos": true
    },
    {
      "episode_number": "2",
      "episode_url": "https://zoroto.com.in/my-hero-academia-4-episode-2/",
      "episode_title": "2",
      "video_sources": [
        "https://gogoanime.com.by/streaming.php?id=my-hero-academia-4-365&ep=8498&server=hd-1&type=sub"
      ],
      "has_videos": true
    },
    {
      "episode_number": "3",
      "episode_url": "https://zoroto.com.in/my-hero-academia-4-episode-3/",
      "episode_title": "3",
      "video_sources": [
        "https://gogoanime.com.by/streaming.php?id=my-hero-academia-4-365&ep=8499&server=hd-1&type=sub"
      ],
      "has_videos": true
    },
    {
      "episode_number": "4",
      "episode_url": "https://zoroto.com.in/my-hero-academia-4-episode-4/",
      "episode_title": "4",
      "video_sources": [
        "https://gogoanime.com.by/streaming.php?id=my-hero-academia-4-365&ep=8500&server=hd-1&type=sub"
      ],
      "has_videos": true
    },
    {
      "episode_number": "5",
      "episode_url": "https://zoroto.com.in/my-hero-academia-4-episode-5/",
      "episode_title": "5",
      "video_sources": [
        "https://gogoanime.com.by/streaming.php?id=my-hero-academia-4-365&ep=8501&server=hd-1&type=sub"
      ],
      "has_videos": true
    },
    {
      "episode_number": "6",
      "episode_url": "https://zoroto.com.in/my-hero-academia-4-episode-6/",
      "episode_title": "6",
      "video_sources": [
        "https://gogoanime.com.by/streaming.php?id=my-hero-academia-4-365&ep=8502&server=hd-1&type=sub"
      ],
      "has_videos": true
    },
    {
      "episode_number": "7",
      "episode_url": "https://zoroto.com.in/my-hero-academia-4-episode-7/",
      "episode_title": "7",
      "video_sources": [
        "https://gogoanime.com.by/streaming.php?id=my-hero-academia-4-365&ep=8503&server=hd-1&type=sub"
      ],
      "has_videos": true
    },
    {
      "episode_number": "8",
      "episode_url": "https://zoroto.com.in/my-hero-academia-4-episode-8/",
      "episode_title": "8",
      "video_sources": [
        "https://gogoanime.com.by/streaming.php?id=my-hero-academia-4-365&ep=8504&server=hd-1&type=sub"
      ],
      "has_videos": true
    },
    {
      "episode_number": "9",
      "episode_url": "https://zoroto.com.in/my-hero-academia-4-episode-9/",
      "episode_title": "9",
      "video_sources": [
        "https://gogoanime.com.by/streaming.php?id=my-hero-academia-4-365&ep=8505&server=hd-1&type=sub"
      ],
      "has_videos": true
    },
    {
      "episode_number": "10",
      "episode_url": "https://zoroto.com.in/my-hero-academia-4-episode-10/",
      "episode_title": "10",
      "video_sources": [
        "https://gogoanime.com.by/streaming.php?id=my-hero-academia-4-365&ep=8506&server=hd-1&type=sub"
      ],
      "has_videos": true
    },
    {
      "episode_number": "11",
      "episode_url": "https://zoroto.com.in/my-hero-academia-4-episode-11/",
      "episode_title": "11",
      "video_sources": [
        "https://gogoanime.com.by/streaming.php?id=my-hero-academia-4-365&ep=8507&server=hd-1&type=sub"
      ],
      "has_videos": true
    },
    {
      "episode_number": "13",
      "episode_url": "https://zoroto.com.in/my-hero-academia-4-episode-13/",
      "episode_title": "13",
      "video_sources": [
        "https://gogoanime.com.by/streaming.php?id=my-hero-academia-4-365&ep=8509&server=hd-1&type=sub"
      ],
      "has_videos": true
    },
    {
      "episode_number": "14",
      "episode_url": "https://zoroto.com.in/my-hero-academia-4-episode-14/",
      "episode_title": "14",
      "video_sources": [
        "https://gogoanime.com.by/streaming.php?id=my-hero-academia-4-365&ep=8510&server=hd-1&type=sub"
      ],
      "has_videos": true
    },
    {
      "episode_number": "15",
      "episode_url": "https://zoroto.com.in/my-hero-academia-4-episode-15/",
      "episode_title": "15",
      "video_sources": [
        "https://gogoanime.com.by/streaming.php?id=my-hero-academia-4-365&ep=8511&server=hd-1&type=sub"
      ],
      "has_videos": true
    },
    {
      "episode_number": "16",
      "episode_url": "https://zoroto.com.in/my-hero-academia-4-episode-16/",
      "episode_title": "16",
      "video_sources": [
        "https://gogoanime.com.by/streaming.php?id=my-hero-academia-4-365&ep=8512&server=hd-1&type=sub"
      ],
      "has_videos": true
    },
    {
      "episode_number": "17",
      "episode_url": "https://zoroto.com.in/my-hero-academia-4-episode-17/",
      "episode_title": "17",
      "video_sources": [
        "https://gogoanime.com.by/streaming.php?id=my-hero-academia-4-365&ep=8513&server=hd-1&type=sub"
      ],
      "has_videos": true
    },
    {
      "episode_number": "18",
      "episode_url": "https://zoroto.com.in/my-hero-academia-4-episode-18/",
      "episode_title": "18",
      "video_sources": [
        "https://gogoanime.com.by/streaming.php?id=my-hero-academia-4-365&ep=8514&server=hd-1&type=sub"
      ],
      "has_videos": true
    },
    {
      "episode_number": "19",
      "episode_url": "https://zoroto.com.in/my-hero-academia-4-episode-19/",
      "episode_title": "19",
      "video_sources": [
        "https://gogoanime.com.by/streaming.php?id=my-hero-academia-4-365&ep=8515&server=hd-1&type=sub"
      ],
      "has_videos": true
    },
    {
      "episode_number": "20",
      "episode_url": "https://zoroto.com.in/my-hero-academia-4-episode-20/",
      "episode_title": "20",
      "video_sources": [
        "https://gogoanime.com.by/streaming.php?id=my-hero-academia-4-365&ep=8516&server=hd-1&type=sub"
      ],
      "has_videos": true
    },
    {
      "episode_number": "21",
      "episode_url": "https://zoroto.com.in/my-hero-academia-4-episode-21/",
      "episode_title": "21",
      "video_sources": [
        "https://gogoanime.com.by/streaming.php?id=my-hero-academia-4-365&ep=8517&server=hd-1&type=sub"
      ],
      "has_videos": true
    },
    {
      "episode_number": "22",
      "episode_url": "https://zoroto.com.in/my-hero-academia-4-episode-22/",
      "episode_title": "22",
      "video_sources": [
        "https://gogoanime.com.by/streaming.php?id=my-hero-academia-4-365&ep=8518&server=hd-1&type=sub"
      ],
      "has_videos": true
    },
    {
      "episode_number": "23",
      "episode_url": "https://zoroto.com.in/my-hero-academia-4-episode-23/",
      "episode_title": "23",
      "video_sources": [
        "https://gogoanime.com.by/streaming.php?id=my-hero-academia-4-365&ep=8519&server=hd-1&type=sub"
      ],
      "has_videos": true
    },
    {
      "episode_number": "24",
      "episode_url": "https://zoroto.com.in/my-hero-academia-4-episode-24/",
      "episode_title": "24",
      "video_sources": [
        "https://gogoanime.com.by/streaming.php?id=my-hero-academia-4-365&ep=8520&server=hd-1&type=sub"
      ],
      "has_videos": true
    },
    {
      "episode_number": "25",
      "episode_url": "https://zoroto.com.in/my-hero-academia-4-episode-25/",
      "episode_title": "25",
      "video_sources": [
        "https://gogoanime.com.by/streaming.php?id=my-hero-academia-4-365&ep=8521&server=hd-1&type=sub"
      ],
      "has_videos": true
    }
  ],
  "scraped_at": "2026-01-30 04:47:02"
}