{
  "title": "My Hero Academia Final Season (2025)",
  "url": "https://zoroto.com.in/anime/my-hero-academia-final-season-2025/",
  "description": "Final season of Boku no Hero Academia.",
  "genres": [],
  "status": null,
  "rating": null,
  "total_episodes": 11,
  "available_episodes": 11,
  "episodes": [
    {
      "episode_number": "1",
      "episode_url": "https://zoroto.com.in/my-hero-academia-final-season-episode-1/",
      "episode_title": "1",
      "video_sources": [
        "https://gogoanime.com.by/streaming.php?id=my-hero-academia-final-season-19930&ep=145522&server=hd-2&type=sub"
      ],
      "has_videos": true
    },
    {
      "episode_number": "2",
      "episode_url": "https://zoroto.com.in/my-hero-academia-final-season-episode-2/",
      "episode_title": "2",
      "video_sources": [
        "https://gogoanime.com.by/streaming.php?id=my-hero-academia-final-season-19930&ep=145841&server=hd-2&type=sub"
      ],
      "has_videos": true
    },
    {
      "episode_number": "3",
      "episode_url": "https://zoroto.com.in/my-hero-academia-final-season-episode-3/",
      "episode_title": "3",
      "video_sources": [
        "https://gogoanime.com.by/streaming.php?id=my-hero-academia-final-season-19930&ep=146130&server=hd-2&type=sub"
      ],
      "has_videos": true
    },
    {
      "episode_number": "4",
      "episode_url": "https://zoroto.com.in/my-hero-academia-final-season-episode-4/",
      "episode_title": "4",
      "video_sources": [
        "https://gogoanime.com.by/streaming.php?id=my-hero-academia-final-season-19930&ep=147253&server=hd-2&type=sub"
      ],
      "has_videos": true
    },
    {
      "episode_number": "5",
      "episode_url": "https://zoroto.com.in/my-hero-academia-final-season-episode-5/",
      "episode_title": "5",
      "video_sources": [
        "https://gogoanime.com.by/streaming.php?id=my-hero-academia-final-season-19930&ep=149149&server=hd-1&type=sub"
      ],
      "has_videos": true
    },
    {
      "episode_number": "6",
      "episode_url": "https://zoroto.com.in/my-hero-academia-final-season-episode-6/",
      "episode_title": "6",
      "video_sources": [
        "https://gogoanime.com.by/streaming.php?id=my-hero-academia-final-season-19930&ep=154817&server=hd-1&type=sub"
      ],
      "has_videos": true
    },
    {
      "episode_number": "7",
      "episode_url": "https://zoroto.com.in/my-hero-academia-final-season-episode-7/",
      "episode_title": "7",
      "video_sources": [
        "https://gogoanime.com.by/streaming.php?id=my-hero-academia-final-season-19930&ep=155641&server=hd-1&type=sub"
      ],
      "has_videos": true
    },
    {
      "episode_number": "8",
      "episode_url": "https://zoroto.com.in/my-hero-academia-final-season-episode-8/",
      "episode_title": "8",
      "video_sources": [
        "https://gogoanime.com.by/streaming.php?id=my-hero-academia-final-season-19930&ep=156549&server=hd-1&type=sub"
      ],
      "has_videos": true
    },
    {
      "episode_number": "9",
      "episode_url": "https://zoroto.com.in/my-hero-academia-final-season-episode-9/",
      "episode_title": "9",
      "video_sources": [
        "https://gogoanime.com.by/streaming.php?id=my-hero-academia-final-season-19930&ep=157841&server=hd-1&type=sub"
      ],
      "has_videos": true
    },
    {
      "episode_number": "10",
      "episode_url": "https://zoroto.com.in/my-hero-academia-final-season-episode-10/",
      "episode_title": "10",
      "video_sources": [
        "https://gogoanime.com.by/streaming.php?id=my-hero-academia-final-season-19930&ep=159185&server=hd-1&type=sub"
      ],
      "has_videos": true
    },
    {
      "episode_number": "11",
      "episode_url": "https://zoroto.com.in/my-hero-academia-final-season-episode-11/",
      "episode_title": "11",
      "video_sources": [
        "https://gogoanime.com.by/streaming.php?id=my-hero-academia-final-season-19930&ep=160029&server=hd-1&type=sub"
      ],
      "has_videos": true
    }
  ],
  "scraped_at": "2026-01-30 04:46:55"
}