{
  "title": "Vampire Dormitory",
  "url": "https://zoroto.com.in/anime/vampire-dormitory/",
  "description": "Homeless and fresh out of employment, Mito Yamamoto faces familiar loneliness and despair. Luck is simply not on Mito’s side; when he stumbles upon a cafe and cuts his hand, a strange server named Ruka Saotome licks the blood from his wound and even dramatically retches at its apparent disgusting taste. Offended and dispirited, Mito runs off to a bridge, hoping to put an end to his misery.But when Mito accidentally slips, he is miraculously saved by Ruka, who reveals he is a vampire. Unable to d",
  "genres": [],
  "status": null,
  "rating": null,
  "total_episodes": 12,
  "available_episodes": 12,
  "episodes": [
    {
      "episode_number": "1",
      "episode_url": "https://zoroto.com.in/vampire-dormitory-episode-1/",
      "episode_title": "1",
      "video_sources": [
        "https://gogoanime.com.by/streaming.php?id=vampire-dormitory-19117&ep=123244&server=hd-2&type=sub"
      ],
      "has_videos": true
    },
    {
      "episode_number": "2",
      "episode_url": "https://zoroto.com.in/vampire-dormitory-episode-2/",
      "episode_title": "2",
      "video_sources": [
        "https://gogoanime.com.by/streaming.php?id=vampire-dormitory-19117&ep=123357&server=hd-2&type=sub"
      ],
      "has_videos": true
    },
    {
      "episode_number": "3",
      "episode_url": "https://zoroto.com.in/vampire-dormitory-episode-3/",
      "episode_title": "3",
      "video_sources": [
        "https://gogoanime.com.by/streaming.php?id=vampire-dormitory-19117&ep=123490&server=hd-2&type=sub"
      ],
      "has_videos": true
    },
    {
      "episode_number": "4",
      "episode_url": "https://zoroto.com.in/vampire-dormitory-episode-4/",
      "episode_title": "4",
      "video_sources": [
        "https://gogoanime.com.by/streaming.php?id=vampire-dormitory-19117&ep=123764&server=hd-2&type=sub"
      ],
      "has_videos": true
    },
    {
      "episode_number": "5",
      "episode_url": "https://zoroto.com.in/vampire-dormitory-episode-5/",
      "episode_title": "5",
      "video_sources": [
        "https://gogoanime.com.by/streaming.php?id=vampire-dormitory-19117&ep=123962&server=hd-2&type=sub"
      ],
      "has_videos": true
    },
    {
      "episode_number": "6",
      "episode_url": "https://zoroto.com.in/vampire-dormitory-episode-6/",
      "episode_title": "6",
      "video_sources": [
        "https://gogoanime.com.by/streaming.php?id=vampire-dormitory-19117&ep=124257&server=hd-2&type=sub"
      ],
      "has_videos": true
    },
    {
      "episode_number": "7",
      "episode_url": "https://zoroto.com.in/vampire-dormitory-episode-7/",
      "episode_title": "7",
      "video_sources": [
        "https://gogoanime.com.by/streaming.php?id=vampire-dormitory-19117&ep=124354&server=hd-2&type=sub"
      ],
      "has_videos": true
    },
    {
      "episode_number": "8",
      "episode_url": "https://zoroto.com.in/vampire-dormitory-episode-8/",
      "episode_title": "8",
      "video_sources": [
        "https://gogoanime.com.by/streaming.php?id=vampire-dormitory-19117&ep=124560&server=hd-2&type=sub"
      ],
      "has_videos": true
    },
    {
      "episode_number": "9",
      "episode_url": "https://zoroto.com.in/vampire-dormitory-episode-9/",
      "episode_title": "9",
      "video_sources": [
        "https://gogoanime.com.by/streaming.php?id=vampire-dormitory-19117&ep=124868&server=hd-2&type=sub"
      ],
      "has_videos": true
    },
    {
      "episode_number": "10",
      "episode_url": "https://zoroto.com.in/vampire-dormitory-episode-10/",
      "episode_title": "10",
      "video_sources": [
        "https://gogoanime.com.by/streaming.php?id=vampire-dormitory-19117&ep=124994&server=hd-2&type=sub"
      ],
      "has_videos": true
    },
    {
      "episode_number": "11",
      "episode_url": "https://zoroto.com.in/vampire-dormitory-episode-11/",
      "episode_title": "11",
      "video_sources": [
        "https://gogoanime.com.by/streaming.php?id=vampire-dormitory-19117&ep=125295&server=hd-2&type=sub"
      ],
      "has_videos": true
    },
    {
      "episode_number": "12",
      "episode_url": "https://zoroto.com.in/vampire-dormitory-episode-12/",
      "episode_title": "12",
      "video_sources": [
        "https://gogoanime.com.by/streaming.php?id=vampire-dormitory-19117&ep=125561&server=hd-2&type=sub"
      ],
      "has_videos": true
    }
  ],
  "scraped_at": "2026-01-30 04:57:42"
}